dii/__init__.py
dii/__main__.py
dii/calculator.py
dii/reader.py
dii/reference.py
dii/viewer.py
dii/visualization.py
dii/data/__init__.py
dii/data/dii_reference.csv
dii_calculator-1.0.13.dist-info/licenses/LICENSE
dii_calculator-1.0.13.dist-info/METADATA
dii_calculator-1.0.13.dist-info/WHEEL
dii_calculator-1.0.13.dist-info/entry_points.txt
dii_calculator-1.0.13.dist-info/top_level.txt
dii_calculator-1.0.13.dist-info/RECORD
