Metadata-Version: 2.4
Name: dii-calculator
Version: 1.0.13
Summary: A Python implementation of the Dietary Inflammatory Index (DII) calculator for nutritional epidemiology research
Author-email: Ted Clark <tedclark94@gmail.com>, Larissa Strath <larissastrath@ufl.edu>
Maintainer-email: Ted Clark <tedclark94@gmail.com>
License-Expression: MIT
Project-URL: Homepage, https://github.com/strathlab-data/DII
Project-URL: Documentation, https://github.com/strathlab-data/DII#readme
Project-URL: Repository, https://github.com/strathlab-data/DII
Project-URL: Issues, https://github.com/strathlab-data/DII/issues
Keywords: dietary inflammatory index,DII,nutrition,epidemiology,inflammation,dietary assessment,NHANES,public health
Classifier: Development Status :: 5 - Production/Stable
Classifier: Intended Audience :: Science/Research
Classifier: Intended Audience :: Healthcare Industry
Classifier: Operating System :: OS Independent
Classifier: Programming Language :: Python :: 3
Classifier: Programming Language :: Python :: 3.10
Classifier: Programming Language :: Python :: 3.11
Classifier: Programming Language :: Python :: 3.12
Classifier: Topic :: Scientific/Engineering :: Medical Science Apps.
Classifier: Topic :: Scientific/Engineering :: Bio-Informatics
Requires-Python: >=3.10
License-File: LICENSE
Requires-Dist: pandas>=1.3.0
Requires-Dist: numpy>=1.20.0
Requires-Dist: scipy>=1.7.0
Requires-Dist: matplotlib>=3.5.0
Provides-Extra: dev
Requires-Dist: pytest>=7.0.0; extra == "dev"
Requires-Dist: pytest-cov>=4.0.0; extra == "dev"
Requires-Dist: black>=23.0.0; extra == "dev"
Requires-Dist: mypy>=1.0.0; extra == "dev"
Requires-Dist: build>=1.0.0; extra == "dev"
Requires-Dist: twine>=4.0.0; extra == "dev"
Requires-Dist: bumpver>=2023.1129; extra == "dev"
Provides-Extra: all
Requires-Dist: dii-calculator[dev]; extra == "all"
Dynamic: license-file
